README.txt
setup.py
inquant/__init__.py
inquant.contentmirror.egg-info/PKG-INFO
inquant.contentmirror.egg-info/SOURCES.txt
inquant.contentmirror.egg-info/dependency_links.txt
inquant.contentmirror.egg-info/entry_points.txt
inquant.contentmirror.egg-info/namespace_packages.txt
inquant.contentmirror.egg-info/not-zip-safe
inquant.contentmirror.egg-info/requires.txt
inquant.contentmirror.egg-info/top_level.txt
inquant/contentmirror/CHANGELOG
inquant/contentmirror/README.rst
inquant/contentmirror/__init__.py
inquant/contentmirror/adapter.py
inquant/contentmirror/configure.zcml
inquant/contentmirror/interfaces.py
inquant/contentmirror/subscriber.py
inquant/contentmirror/traverse.py
inquant/contentmirror/browser/__init__.py
inquant/contentmirror/tests/__init__.py
inquant/contentmirror/tests/base.py
inquant/contentmirror/tests/test_doctests.py
inquant/contentmirror/tests/test_traverser.py
