Metadata-Version: 1.0
Name: inquant.contentmirror
Version: 0.1
Summary: mirror plone content transparently in a plone site
Home-page: https://svn.plone.org/svn/collective/inquant.contentmirror/trunk
Author: Stefan Eletzhofer
Author-email: stefan.eletzhofer@inquant.de
License: GPL
Platform: UNKNOWN
Classifier: Framework :: Plone
Classifier: Framework :: Zope2
Classifier: Framework :: Zope3
Classifier: Programming Language :: Python
Classifier: Topic :: Software Development :: Libraries :: Python Modules
